zodiaco/__init__.py
zodiaco/signos/__init__.py
zodiaco/signos/getSignos.py
zodiaco-0.0.1.dist-info/METADATA
zodiaco-0.0.1.dist-info/WHEEL
zodiaco-0.0.1.dist-info/top_level.txt
zodiaco-0.0.1.dist-info/RECORD
