Metadata-Version: 2.1
Name: zodiaco
Version: 0.0.1
Summary: Determina seu signo com base na sua data de nascimento
Home-page: https://github.com/jcbdoliveira/pacotes-python-DIO-Bootcamp-Unimed-BH
Author: Julio Cesar Bueno de Oliveira
Author-email: jcboliveira@gmail.com	
Requires-Python: >=3.8
